unpack/__init__.py
unpack/unpack.py
unpack-0.0.8.dist-info/METADATA
unpack-0.0.8.dist-info/WHEEL
unpack-0.0.8.dist-info/top_level.txt
unpack-0.0.8.dist-info/RECORD
