Metadata-Version: 2.1
Name: unpack
Version: 0.0.8
Summary: Library for unpacking request object for 3deposit services
Home-page: UNKNOWN
Author: Mihir Joshi
Author-email: idealab@library.illinois.edu
License: UNKNOWN
Platform: UNKNOWN
Classifier: Programming Language :: Python :: 3
Classifier: License :: OSI Approved :: MIT License
Classifier: Operating System :: OS Independent
